{"id":"beta","benchmarks":{"encoding":{"Ok":{"runs":[{"stats":{"stats":[null,1067813016.0,10508.0,null,1566194169.0,140768.0,279.072193,null,0.287683515,279.069919]},"self_profile":null,"check":true,"release":false,"state":"Clean"},{"stats":{"stats":[null,1323075209.0,16429.0,null,1943900425.0,166312.0,349.346968,null,0.354344892,349.346371]},"self_profile":null,"check":true,"release":false,"state":"IncrementalStart"},{"stats":{"stats":[null,423766234.0,15313.0,null,742020932.0,147340.0,126.83992,null,0.15094026,126.838527]},"self_profile":null,"check":true,"release":false,"state":"IncrementalClean"},{"stats":{"stats":[null,466517279.0,15849.0,null,787297919.0,157244.0,136.618249,null,0.136386517,136.618022]},"self_profile":null,"check":true,"release":false,"state":{"IncrementalPatched":{"index":0,"name":"println","path":"0-println.patch"}}},{"stats":{"stats":[null,4708258478.0,28642.0,null,6668411963.0,209604.0,1230.234568,null,0.672165757,1230.227912]},"self_profile":null,"check":false,"release":false,"state":"Clean"},{"stats":{"stats":[null,5858691967.0,37522.0,null,8009912652.0,241276.0,1569.089912,null,0.751728475,1569.042779]},"self_profile":null,"check":false,"release":false,"state":"IncrementalStart"},{"stats":{"stats":[null,608711604.0,20719.0,null,981367961.0,171988.0,201.93843,null,0.185278872,201.813637]},"self_profile":null,"check":false,"release":false,"state":"IncrementalClean"},{"stats":{"stats":[null,671860383.0,21118.0,null,1064238939.0,181812.0,216.257613,null,0.195619359,216.151858]},"self_profile":null,"check":false,"release":false,"state":{"IncrementalPatched":{"index":0,"name":"println","path":"0-println.patch"}}},{"stats":{"stats":[null,13963925853.0,34677.0,null,16585531076.0,211128.0,3613.210307,null,1.003345107,3613.210653]},"self_profile":null,"check":false,"release":true,"state":"Clean"},{"stats":{"stats":[null,15394869323.0,40323.0,null,17867141197.0,237284.0,4022.683718,null,1.064747919,4022.669638]},"self_profile":null,"check":false,"release":true,"state":"IncrementalStart"},{"stats":{"stats":[null,614819532.0,20438.0,null,995245246.0,172480.0,193.176319,null,0.180075902,193.114875]},"self_profile":null,"check":false,"release":true,"state":"IncrementalClean"},{"stats":{"stats":[null,977510810.0,21323.0,null,1487519926.0,177240.0,288.091767,null,0.258315943,288.023999]},"self_profile":null,"check":false,"release":true,"state":{"IncrementalPatched":{"index":0,"name":"println","path":"0-println.patch"}}}],"name":"encoding"}},"futures":{"Ok":{"runs":[{"stats":{"stats":[null,1869927164.0,10965.0,null,2799309927.0,140480.0,477.310625,null,0.487944986,477.308231]},"self_profile":null,"check":true,"release":false,"state":"Clean"},{"stats":{"stats":[null,2218059676.0,17870.0,null,3307761418.0,169888.0,570.407288,null,0.576282469,570.407395]},"self_profile":null,"check":true,"release":false,"state":"IncrementalStart"},{"stats":{"stats":[null,404482929.0,16630.0,null,652332529.0,151500.0,123.274375,null,0.122534928,123.272246]},"self_profile":null,"check":true,"release":false,"state":"IncrementalClean"},{"stats":{"stats":[null,412260871.0,16682.0,null,658919401.0,152252.0,125.109786,null,0.124093236,125.108584]},"self_profile":null,"check":true,"release":false,"state":{"IncrementalPatched":{"index":0,"name":"println","path":"0-println.patch"}}},{"stats":{"stats":[null,2758932092.0,16370.0,null,3947238338.0,167236.0,716.132734,null,0.585249054,716.122024]},"self_profile":null,"check":false,"release":false,"state":"Clean"},{"stats":{"stats":[null,3379558659.0,24934.0,null,4717667519.0,199140.0,891.352716,null,0.703329805,891.33002]},"self_profile":null,"check":false,"release":false,"state":"IncrementalStart"},{"stats":{"stats":[null,503550589.0,19324.0,null,777546995.0,166408.0,160.477247,null,0.151929514,160.432256]},"self_profile":null,"check":false,"release":false,"state":"IncrementalClean"},{"stats":{"stats":[null,512542326.0,19404.0,null,784248429.0,167228.0,161.872835,null,0.153769548,161.83148]},"self_profile":null,"check":false,"release":false,"state":{"IncrementalPatched":{"index":0,"name":"println","path":"0-println.patch"}}},{"stats":{"stats":[null,4275492626.0,19298.0,null,5343364731.0,163912.0,1115.80242,null,0.640491976,1115.782574]},"self_profile":null,"check":false,"release":true,"state":"Clean"},{"stats":{"stats":[null,4660860056.0,26764.0,null,5945550796.0,194128.0,1222.068298,null,0.731276549,1222.040426]},"self_profile":null,"check":false,"release":true,"state":"IncrementalStart"},{"stats":{"stats":[null,499899082.0,19195.0,null,773723667.0,166492.0,155.282479,null,0.147404433,155.256418]},"self_profile":null,"check":false,"release":true,"state":"IncrementalClean"},{"stats":{"stats":[null,505909166.0,19127.0,null,779803750.0,166536.0,157.995057,null,0.150049454,157.972848]},"self_profile":null,"check":false,"release":true,"state":{"IncrementalPatched":{"index":0,"name":"println","path":"0-println.patch"}}}],"name":"futures"}},"html5ever":{"Ok":{"runs":[{"stats":{"stats":[null,4435862463.0,39901.0,null,7473473681.0,257720.0,1142.911341,null,1.187996043,1142.909972]},"self_profile":null,"check":true,"release":false,"state":"Clean"},{"stats":{"stats":[null,5242249659.0,44568.0,null,9031532643.0,278672.0,1350.149246,null,1.383083756,1350.149283]},"self_profile":null,"check":true,"release":false,"state":"IncrementalStart"},{"stats":{"stats":[null,1381894879.0,33109.0,null,2679775619.0,218912.0,386.501425,null,0.384612343,386.499953]},"self_profile":null,"check":true,"release":false,"state":"IncrementalClean"},{"stats":{"stats":[null,1653076412.0,34179.0,null,3055681218.0,231508.0,452.405344,null,0.450675379,452.405064]},"self_profile":null,"check":true,"release":false,"state":{"IncrementalPatched":{"index":0,"name":"println","path":"0-println.patch"}}},{"stats":{"stats":[null,7100269072.0,53004.0,null,11330746325.0,291496.0,1840.777393,null,1.483368383,1840.770675]},"self_profile":null,"check":false,"release":false,"state":"Clean"},{"stats":{"stats":[null,8429632411.0,67490.0,null,13554016641.0,335476.0,2212.071198,null,1.768675482,2212.016355]},"self_profile":null,"check":false,"release":false,"state":"IncrementalStart"},{"stats":{"stats":[null,1699418706.0,43222.0,null,3092180011.0,262448.0,500.471656,null,0.481975893,500.360045]},"self_profile":null,"check":false,"release":false,"state":"IncrementalClean"},{"stats":{"stats":[null,2012623926.0,44288.0,null,3529615970.0,281760.0,574.911606,null,0.554334854,574.81314]},"self_profile":null,"check":false,"release":false,"state":{"IncrementalPatched":{"index":0,"name":"println","path":"0-println.patch"}}},{"stats":{"stats":[null,19652972451.0,90625.0,null,25409064980.0,409988.0,5178.933171,null,1.850106896,5178.950902]},"self_profile":null,"check":false,"release":true,"state":"Clean"},{"stats":{"stats":[null,19698628795.0,75600.0,null,24691694174.0,357436.0,5121.804761,null,1.983992463,5121.792912]},"self_profile":null,"check":false,"release":true,"state":"IncrementalStart"},{"stats":{"stats":[null,1796783974.0,43351.0,null,3216138563.0,264300.0,520.547348,null,0.484898824,520.47144]},"self_profile":null,"check":false,"release":true,"state":"IncrementalClean"},{"stats":{"stats":[null,2204899691.0,45042.0,null,3763121285.0,288716.0,635.715783,null,0.587005336,635.638763]},"self_profile":null,"check":false,"release":true,"state":{"IncrementalPatched":{"index":0,"name":"println","path":"0-println.patch"}}}],"name":"html5ever"}},"inflate":{"Ok":{"runs":[{"stats":{"stats":[null,3534382345.0,28643.0,null,7979149771.0,202444.0,920.427264,null,0.931174488,920.42605]},"self_profile":null,"check":true,"release":false,"state":"Clean"},{"stats":{"stats":[null,3774766060.0,34876.0,null,8478335961.0,212296.0,983.481175,null,0.988733931,983.479811]},"self_profile":null,"check":true,"release":false,"state":"IncrementalStart"},{"stats":{"stats":[null,349682767.0,11979.0,null,618533591.0,130420.0,102.969007,null,0.123719895,102.967615]},"self_profile":null,"check":true,"release":false,"state":"IncrementalClean"},{"stats":{"stats":[null,3707707471.0,36801.0,null,8384854223.0,238212.0,965.13985,null,0.96947948,965.138247]},"self_profile":null,"check":true,"release":false,"state":{"IncrementalPatched":{"index":0,"name":"println","path":"0-println.patch"}}},{"stats":{"stats":[null,6350409079.0,51411.0,null,12112790235.0,276508.0,1652.155265,null,1.518625322,1652.148362]},"self_profile":null,"check":false,"release":false,"state":"Clean"},{"stats":{"stats":[null,6861320500.0,61661.0,null,12922406510.0,312172.0,1797.210147,null,1.592424375,1797.187441]},"self_profile":null,"check":false,"release":false,"state":"IncrementalStart"},{"stats":{"stats":[null,479902950.0,15998.0,null,839972256.0,152108.0,149.648246,null,0.163427818,149.609775]},"self_profile":null,"check":false,"release":false,"state":"IncrementalClean"},{"stats":{"stats":[null,6794590783.0,57880.0,null,12808679754.0,299744.0,1795.448272,null,1.571500825,1795.431843]},"self_profile":null,"check":false,"release":false,"state":{"IncrementalPatched":{"index":0,"name":"println","path":"0-println.patch"}}},{"stats":{"stats":[null,21509651408.0,66989.0,null,40688002425.0,333516.0,5444.435254,null,5.262339973,5444.402672]},"self_profile":null,"check":false,"release":true,"state":"Clean"},{"stats":{"stats":[null,21076658221.0,72932.0,null,40122717647.0,331372.0,5319.948054,null,5.085892314,5319.931899]},"self_profile":null,"check":false,"release":true,"state":"IncrementalStart"},{"stats":{"stats":[null,465943320.0,15743.0,null,821888662.0,151824.0,141.288452,null,0.158715713,141.259524]},"self_profile":null,"check":false,"release":true,"state":"IncrementalClean"},{"stats":{"stats":[null,20459597533.0,70278.0,null,39729481815.0,317296.0,5162.344122,null,5.148285191,5162.31768]},"self_profile":null,"check":false,"release":true,"state":{"IncrementalPatched":{"index":0,"name":"println","path":"0-println.patch"}}}],"name":"inflate"}},"piston-image":{"Ok":{"runs":[{"stats":{"stats":[null,4348526841.0,23733.0,null,6106306997.0,195948.0,1101.924309,null,1.130012012,1101.920824]},"self_profile":null,"check":true,"release":false,"state":"Clean"},{"stats":{"stats":[null,5204568701.0,35758.0,null,7362267255.0,245204.0,1326.924311,null,1.349947481,1326.923009]},"self_profile":null,"check":true,"release":false,"state":"IncrementalStart"},{"stats":{"stats":[null,1051103008.0,32167.0,null,1610827798.0,216260.0,300.61622,null,0.312334897,300.614717]},"self_profile":null,"check":true,"release":false,"state":"IncrementalClean"},{"stats":{"stats":[null,1122236878.0,32454.0,null,1681401974.0,231700.0,322.507695,null,0.313862857,322.505736]},"self_profile":null,"check":true,"release":false,"state":{"IncrementalPatched":{"index":0,"name":"println","path":"0-println.patch"}}},{"stats":{"stats":[null,21601888423.0,83781.0,null,30117528236.0,405184.0,5633.210448,null,2.452971458,5633.201185]},"self_profile":null,"check":false,"release":false,"state":"Clean"},{"stats":{"stats":[null,24709085649.0,91655.0,null,33233605020.0,418676.0,6469.994142,null,2.808370966,6469.910506]},"self_profile":null,"check":false,"release":false,"state":"IncrementalStart"},{"stats":{"stats":[null,2020399365.0,51471.0,null,2892437582.0,295752.0,613.23065,null,0.592353291,613.03712]},"self_profile":null,"check":false,"release":false,"state":"IncrementalClean"},{"stats":{"stats":[null,2230937952.0,52983.0,null,3152299972.0,316652.0,665.121992,null,0.597762522,664.908466]},"self_profile":null,"check":false,"release":false,"state":{"IncrementalPatched":{"index":0,"name":"println","path":"0-println.patch"}}},{"stats":{"stats":[null,97841770334.0,92496.0,null,105827242675.0,421164.0,25483.513954,null,4.420406261,25483.545681]},"self_profile":null,"check":false,"release":true,"state":"Clean"},{"stats":{"stats":[null,104898013815.0,100745.0,null,109556658944.0,441292.0,27415.182686,null,4.278592058,27415.240538]},"self_profile":null,"check":false,"release":true,"state":"IncrementalStart"},{"stats":{"stats":[null,2131353458.0,53163.0,null,3033566925.0,305292.0,629.755991,null,0.598583863,629.640201]},"self_profile":null,"check":false,"release":true,"state":"IncrementalClean"},{"stats":{"stats":[null,3607794128.0,57717.0,null,5046643518.0,333152.0,1009.686065,null,0.909715012,1009.550714]},"self_profile":null,"check":false,"release":true,"state":{"IncrementalPatched":{"index":0,"name":"println","path":"0-println.patch"}}}],"name":"piston-image"}},"regex":{"Ok":{"runs":[{"stats":{"stats":[null,2291103114.0,16873.0,null,2981552133.0,167204.0,587.325021,null,0.612277739,587.324109]},"self_profile":null,"check":true,"release":false,"state":"Clean"},{"stats":{"stats":[null,2815510693.0,26098.0,null,3734014384.0,204652.0,736.437517,null,0.742086877,736.436163]},"self_profile":null,"check":true,"release":false,"state":"IncrementalStart"},{"stats":{"stats":[null,660721218.0,23410.0,null,1040723112.0,179340.0,196.216546,null,0.19210738,196.214884]},"self_profile":null,"check":true,"release":false,"state":"IncrementalClean"},{"stats":{"stats":[null,1144449756.0,25127.0,null,1612203035.0,201252.0,316.508761,null,0.313003605,316.5075]},"self_profile":null,"check":true,"release":false,"state":{"IncrementalPatched":{"index":0,"name":"compile one","path":"0-compile-one.patch"}}},{"stats":{"stats":[null,695130304.0,23797.0,null,1071020637.0,189100.0,203.61493,null,0.214837165,203.612398]},"self_profile":null,"check":true,"release":false,"state":{"IncrementalPatched":{"index":1,"name":"is valid cap letter","path":"1-is-valid-cap-letter.patch"}}},{"stats":{"stats":[null,722167158.0,23822.0,null,1100613378.0,189684.0,211.073725,null,0.207061183,211.071832]},"self_profile":null,"check":true,"release":false,"state":{"IncrementalPatched":{"index":2,"name":"expand","path":"2-expand.patch"}}},{"stats":{"stats":[null,1155214792.0,25177.0,null,1628453847.0,201588.0,319.543086,null,0.31584435,319.542653]},"self_profile":null,"check":true,"release":false,"state":{"IncrementalPatched":{"index":3,"name":"Compiler new","path":"3-Compiler-new.patch"}}},{"stats":{"stats":[null,1151593079.0,25197.0,null,1624808219.0,201588.0,317.544497,null,0.32806793,317.542426]},"self_profile":null,"check":true,"release":false,"state":{"IncrementalPatched":{"index":4,"name":"reverse","path":"4-reverse.patch"}}},{"stats":{"stats":[null,677776924.0,23533.0,null,1055754779.0,185540.0,199.720471,null,0.196052088,199.720086]},"self_profile":null,"check":true,"release":false,"state":{"IncrementalPatched":{"index":5,"name":"byte frequencies","path":"5-byte-frequencies.patch"}}},{"stats":{"stats":[null,939184528.0,24020.0,null,1376223134.0,190488.0,266.013041,null,0.262136146,266.011038]},"self_profile":null,"check":true,"release":false,"state":{"IncrementalPatched":{"index":6,"name":"sparse set","path":"6-sparse-set.patch"}}},{"stats":{"stats":[null,789786791.0,23783.0,null,1182156777.0,189292.0,225.92047,null,0.244868222,225.918426]},"self_profile":null,"check":true,"release":false,"state":{"IncrementalPatched":{"index":7,"name":"Job","path":"7-Job.patch"}}},{"stats":{"stats":[null,867547583.0,24016.0,null,1261319162.0,196556.0,249.920151,null,0.245878157,249.918147]},"self_profile":null,"check":true,"release":false,"state":{"IncrementalPatched":{"index":8,"name":"println","path":"8-println.patch"}}},{"stats":{"stats":[null,16018075565.0,75375.0,null,20486531673.0,368308.0,4228.051156,null,1.580076269,4228.048094]},"self_profile":null,"check":false,"release":false,"state":"Clean"},{"stats":{"stats":[null,19003261878.0,79637.0,null,23080639116.0,394080.0,5036.357478,null,1.599665881,5036.316777]},"self_profile":null,"check":false,"release":false,"state":"IncrementalStart"},{"stats":{"stats":[null,1145301656.0,35160.0,null,1628152850.0,228316.0,362.642351,null,0.333616507,362.527185]},"self_profile":null,"check":false,"release":false,"state":"IncrementalClean"},{"stats":{"stats":[null,4281768615.0,53692.0,null,5737000723.0,304272.0,1195.831068,null,0.655040795,1195.724373]},"self_profile":null,"check":false,"release":false,"state":{"IncrementalPatched":{"index":0,"name":"compile one","path":"0-compile-one.patch"}}},{"stats":{"stats":[null,1212950441.0,35991.0,null,1694860653.0,241684.0,379.21823,null,0.342879901,379.054483]},"self_profile":null,"check":false,"release":false,"state":{"IncrementalPatched":{"index":1,"name":"is valid cap letter","path":"1-is-valid-cap-letter.patch"}}},{"stats":{"stats":[null,1736307281.0,39354.0,null,2362384379.0,254512.0,522.916324,null,0.441233701,522.785009]},"self_profile":null,"check":false,"release":false,"state":{"IncrementalPatched":{"index":2,"name":"expand","path":"2-expand.patch"}}},{"stats":{"stats":[null,4397619147.0,53315.0,null,5768563714.0,305296.0,1220.770031,null,0.662390095,1220.653974]},"self_profile":null,"check":false,"release":false,"state":{"IncrementalPatched":{"index":3,"name":"Compiler new","path":"3-Compiler-new.patch"}}},{"stats":{"stats":[null,4307198484.0,51606.0,null,5751320973.0,300976.0,1202.990528,null,0.682219257,1202.879593]},"self_profile":null,"check":false,"release":false,"state":{"IncrementalPatched":{"index":4,"name":"reverse","path":"4-reverse.patch"}}},{"stats":{"stats":[null,1153934797.0,35357.0,null,1650797887.0,232048.0,367.236925,null,0.336998284,367.104275]},"self_profile":null,"check":false,"release":false,"state":{"IncrementalPatched":{"index":5,"name":"byte frequencies","path":"5-byte-frequencies.patch"}}},{"stats":{"stats":[null,13251525658.0,81484.0,null,16337746896.0,398024.0,3561.870173,null,0.9435777,3561.807888]},"self_profile":null,"check":false,"release":false,"state":{"IncrementalPatched":{"index":6,"name":"sparse set","path":"6-sparse-set.patch"}}},{"stats":{"stats":[null,12691987768.0,81765.0,null,15716274727.0,397360.0,3419.833592,null,0.875866363,3419.776812]},"self_profile":null,"check":false,"release":false,"state":{"IncrementalPatched":{"index":7,"name":"Job","path":"7-Job.patch"}}},{"stats":{"stats":[null,2095111357.0,42129.0,null,3034303562.0,261168.0,613.238431,null,0.455426551,613.077999]},"self_profile":null,"check":false,"release":false,"state":{"IncrementalPatched":{"index":8,"name":"println","path":"8-println.patch"}}},{"stats":{"stats":[null,55946850396.0,66443.0,null,61951593779.0,332484.0,14612.753688,null,3.006952772,14612.77321]},"self_profile":null,"check":false,"release":true,"state":"Clean"},{"stats":{"stats":[null,61320530997.0,78338.0,null,65352710549.0,371556.0,16104.15276,null,3.096042107,16104.202118]},"self_profile":null,"check":false,"release":true,"state":"IncrementalStart"},{"stats":{"stats":[null,1159948891.0,35118.0,null,1667932481.0,230912.0,356.453735,null,0.328358943,356.378608]},"self_profile":null,"check":false,"release":true,"state":"IncrementalClean"},{"stats":{"stats":[null,34753894786.0,75897.0,null,38149830618.0,368404.0,9133.684767,null,1.852646576,9133.695306]},"self_profile":null,"check":false,"release":true,"state":{"IncrementalPatched":{"index":0,"name":"compile one","path":"0-compile-one.patch"}}},{"stats":{"stats":[null,1388732540.0,36286.0,null,1949193991.0,243436.0,418.134456,null,0.35346571,418.029346]},"self_profile":null,"check":false,"release":true,"state":{"IncrementalPatched":{"index":1,"name":"is valid cap letter","path":"1-is-valid-cap-letter.patch"}}},{"stats":{"stats":[null,1440316415.0,36305.0,null,1981764386.0,243920.0,431.511086,null,0.366369133,431.415638]},"self_profile":null,"check":false,"release":true,"state":{"IncrementalPatched":{"index":2,"name":"expand","path":"2-expand.patch"}}},{"stats":{"stats":[null,34715072981.0,76033.0,null,38180142738.0,368904.0,9125.19571,null,1.85813191,9125.209871]},"self_profile":null,"check":false,"release":true,"state":{"IncrementalPatched":{"index":3,"name":"Compiler new","path":"3-Compiler-new.patch"}}},{"stats":{"stats":[null,34686516852.0,76065.0,null,38162085780.0,368936.0,9108.598925,null,1.853352404,9108.609411]},"self_profile":null,"check":false,"release":true,"state":{"IncrementalPatched":{"index":4,"name":"reverse","path":"4-reverse.patch"}}},{"stats":{"stats":[null,1191327280.0,35392.0,null,1688526575.0,234888.0,363.149783,null,0.33299878,363.047296]},"self_profile":null,"check":false,"release":true,"state":{"IncrementalPatched":{"index":5,"name":"byte frequencies","path":"5-byte-frequencies.patch"}}},{"stats":{"stats":[null,44202303129.0,77315.0,null,50421414766.0,374436.0,11586.626399,null,2.126823917,11586.64541]},"self_profile":null,"check":false,"release":true,"state":{"IncrementalPatched":{"index":6,"name":"sparse set","path":"6-sparse-set.patch"}}},{"stats":{"stats":[null,48144764541.0,78943.0,null,53608058854.0,377552.0,12620.630956,null,2.163266591,12620.667808]},"self_profile":null,"check":false,"release":true,"state":{"IncrementalPatched":{"index":7,"name":"Job","path":"7-Job.patch"}}},{"stats":{"stats":[null,7703752308.0,51290.0,null,11705337683.0,281336.0,2019.531365,null,1.463695139,2019.441962]},"self_profile":null,"check":false,"release":true,"state":{"IncrementalPatched":{"index":8,"name":"println","path":"8-println.patch"}}}],"name":"regex"}},"style-servo":{"Ok":{"runs":[{"stats":{"stats":[null,74995514011.0,289366.0,null,97859350536.0,1205088.0,18777.173269,null,18.815166881,18777.178615]},"self_profile":null,"check":true,"release":false,"state":"Clean"},{"stats":{"stats":[null,90909036819.0,470533.0,null,120024187480.0,1902944.0,22958.636803,null,22.985728851,22958.644106]},"self_profile":null,"check":true,"release":false,"state":"IncrementalStart"},{"stats":{"stats":[null,30910660674.0,445952.0,null,40486848364.0,1879796.0,8102.291579,null,7.824835784,8102.289205]},"self_profile":null,"check":true,"release":false,"state":"IncrementalClean"},{"stats":{"stats":[null,56513251085.0,519071.0,null,74041925531.0,2168044.0,14412.708413,null,14.137229981,14412.70712]},"self_profile":null,"check":true,"release":false,"state":{"IncrementalPatched":{"index":0,"name":"println","path":"0-println.patch"}}},{"stats":{"stats":[null,57814289600.0,523576.0,null,73418939595.0,2189940.0,14921.887929,null,14.633973001,14921.887796]},"self_profile":null,"check":true,"release":false,"state":{"IncrementalPatched":{"index":1,"name":"b9b3e592dd cherry picked","path":"1-b9b3e592dd-cherry-picked.patch"}}},{"stats":{"stats":[null,200559152628.0,686413.0,null,261583034553.0,2562328.0,51340.360494,null,29.204647634,51340.378864]},"self_profile":null,"check":false,"release":false,"state":"Clean"},{"stats":{"stats":[null,325388933438.0,1009812.0,null,476701601698.0,3159212.0,84640.693709,null,43.615648335,84640.114764]},"self_profile":null,"check":false,"release":false,"state":"IncrementalStart"},{"stats":{"stats":[null,39545632651.0,609764.0,null,50968289229.0,3066464.0,11020.755024,null,10.461687155,11019.35296]},"self_profile":null,"check":false,"release":false,"state":"IncrementalClean"},{"stats":{"stats":[null,199805439216.0,946148.0,null,288960418021.0,3640536.0,52530.007544,null,26.943497617,52529.381891]},"self_profile":null,"check":false,"release":false,"state":{"IncrementalPatched":{"index":0,"name":"println","path":"0-println.patch"}}},{"stats":{"stats":[null,256445595197.0,1080215.0,null,376521679467.0,3716220.0,67426.851577,null,31.696668501,67426.196481]},"self_profile":null,"check":false,"release":false,"state":{"IncrementalPatched":{"index":1,"name":"b9b3e592dd cherry picked","path":"1-b9b3e592dd-cherry-picked.patch"}}},{"stats":{"stats":[null,664431113307.0,722355.0,null,732116890693.0,2290704.0,173185.437709,null,39.914062793,173185.631022]},"self_profile":null,"check":false,"release":true,"state":"Clean"},{"stats":{"stats":[null,979419604546.0,1053806.0,null,1126146305303.0,2976168.0,257322.911083,null,47.20686284,257323.384993]},"self_profile":null,"check":false,"release":true,"state":"IncrementalStart"},{"stats":{"stats":[null,35853136172.0,601590.0,null,44966833888.0,2464712.0,9832.85316,null,9.189585456,9831.615393]},"self_profile":null,"check":false,"release":true,"state":"IncrementalClean"},{"stats":{"stats":[null,833636252767.0,1083702.0,null,963782865666.0,3205016.0,220196.528847,null,34.012108825,220197.06915]},"self_profile":null,"check":false,"release":true,"state":{"IncrementalPatched":{"index":0,"name":"println","path":"0-println.patch"}}},{"stats":{"stats":[null,924443214332.0,1124885.0,null,1053846062504.0,3315308.0,244140.28036,null,36.941763671,244140.59437]},"self_profile":null,"check":false,"release":true,"state":{"IncrementalPatched":{"index":1,"name":"b9b3e592dd cherry picked","path":"1-b9b3e592dd-cherry-picked.patch"}}}],"name":"style-servo"}},"syn":{"Ok":{"runs":[{"stats":{"stats":[null,1702823581.0,13561.0,null,2453568843.0,149972.0,444.879684,null,0.459962339,444.877208]},"self_profile":null,"check":true,"release":false,"state":"Clean"},{"stats":{"stats":[null,2096836512.0,20193.0,null,3052811064.0,178520.0,550.346917,null,0.558222928,550.345247]},"self_profile":null,"check":true,"release":false,"state":"IncrementalStart"},{"stats":{"stats":[null,626830070.0,19599.0,null,1036520655.0,161876.0,183.948299,null,0.201022685,183.946746]},"self_profile":null,"check":true,"release":false,"state":"IncrementalClean"},{"stats":{"stats":[null,738438324.0,20125.0,null,1151230547.0,172932.0,213.360681,null,0.21098686,213.358576]},"self_profile":null,"check":true,"release":false,"state":{"IncrementalPatched":{"index":0,"name":"println","path":"0-println.patch"}}},{"stats":{"stats":[null,7291054195.0,35712.0,null,10051841440.0,232708.0,1925.317467,null,0.912094498,1925.311961]},"self_profile":null,"check":false,"release":false,"state":"Clean"},{"stats":{"stats":[null,8725885084.0,44955.0,null,12167949896.0,263748.0,2333.466325,null,1.107476854,2333.417125]},"self_profile":null,"check":false,"release":false,"state":"IncrementalStart"},{"stats":{"stats":[null,933264008.0,26078.0,null,1449384669.0,190460.0,290.417391,null,0.274118671,290.333232]},"self_profile":null,"check":false,"release":false,"state":"IncrementalClean"},{"stats":{"stats":[null,1425267575.0,30959.0,null,2061757419.0,225672.0,424.665278,null,0.337470976,424.576382]},"self_profile":null,"check":false,"release":false,"state":{"IncrementalPatched":{"index":0,"name":"println","path":"0-println.patch"}}},{"stats":{"stats":[null,34749283567.0,42253.0,null,37374444739.0,237396.0,9090.008449,null,1.91542581,9090.008975]},"self_profile":null,"check":false,"release":true,"state":"Clean"},{"stats":{"stats":[null,31106984469.0,47519.0,null,33112306642.0,255852.0,8170.002088,null,1.823012782,8170.008714]},"self_profile":null,"check":false,"release":true,"state":"IncrementalStart"},{"stats":{"stats":[null,959254413.0,25840.0,null,1469577548.0,191592.0,289.676924,null,0.268571486,289.612638]},"self_profile":null,"check":false,"release":true,"state":"IncrementalClean"},{"stats":{"stats":[null,13603216263.0,43559.0,null,15295732173.0,244236.0,3605.47831,null,0.903823811,3605.452577]},"self_profile":null,"check":false,"release":true,"state":{"IncrementalPatched":{"index":0,"name":"println","path":"0-println.patch"}}}],"name":"syn"}},"tokio-webpush-simple":{"Ok":{"runs":[{"stats":{"stats":[null,771578785.0,9962.0,null,1130589070.0,147700.0,206.395325,null,0.246602746,206.393388]},"self_profile":null,"check":true,"release":false,"state":"Clean"},{"stats":{"stats":[null,1007145674.0,15715.0,null,1510477637.0,171504.0,273.750545,null,0.279917697,273.749773]},"self_profile":null,"check":true,"release":false,"state":"IncrementalStart"},{"stats":{"stats":[null,262462160.0,13904.0,null,452168681.0,144268.0,85.979287,null,0.104940424,85.978166]},"self_profile":null,"check":true,"release":false,"state":"IncrementalClean"},{"stats":{"stats":[null,647420291.0,16792.0,null,940527964.0,176244.0,186.409375,null,0.188335821,186.409226]},"self_profile":null,"check":true,"release":false,"state":{"IncrementalPatched":{"index":0,"name":"println","path":"0-println.patch"}}},{"stats":{"stats":[null,601611593.0,16653.0,null,884333228.0,175656.0,175.07047,null,0.199123298,175.069503]},"self_profile":null,"check":true,"release":false,"state":{"IncrementalPatched":{"index":1,"name":"minor change","path":"1-minor-change.patch"}}},{"stats":{"stats":[null,10276071833.0,82295.0,null,14315683508.0,282176.0,2789.240697,null,1.51347031,2789.222335]},"self_profile":null,"check":false,"release":false,"state":"Clean"},{"stats":{"stats":[null,12402028746.0,92309.0,null,17233120689.0,304880.0,3376.621087,null,1.768514806,3376.507789]},"self_profile":null,"check":false,"release":false,"state":"IncrementalStart"},{"stats":{"stats":[null,2760825617.0,74792.0,null,4299165267.0,235988.0,878.489661,null,0.846919152,878.324731]},"self_profile":null,"check":false,"release":false,"state":"IncrementalClean"},{"stats":{"stats":[null,11731671978.0,94682.0,null,16180256637.0,314292.0,3208.481276,null,1.576771268,3208.393267]},"self_profile":null,"check":false,"release":false,"state":{"IncrementalPatched":{"index":0,"name":"println","path":"0-println.patch"}}},{"stats":{"stats":[null,11644773983.0,95521.0,null,16136683790.0,318900.0,3193.610043,null,1.562282457,3193.51087]},"self_profile":null,"check":false,"release":false,"state":{"IncrementalPatched":{"index":1,"name":"minor change","path":"1-minor-change.patch"}}},{"stats":{"stats":[null,56435263355.0,74191.0,null,60151134846.0,297540.0,14796.249601,null,2.268169039,14796.252663]},"self_profile":null,"check":false,"release":true,"state":"Clean"},{"stats":{"stats":[null,57000386243.0,76906.0,null,60104486737.0,305188.0,15007.944911,null,2.148316433,15007.947115]},"self_profile":null,"check":false,"release":true,"state":"IncrementalStart"},{"stats":{"stats":[null,1413478445.0,48658.0,null,2095454409.0,239776.0,454.717477,null,0.419125077,454.571585]},"self_profile":null,"check":false,"release":true,"state":"IncrementalClean"},{"stats":{"stats":[null,55907523703.0,78668.0,null,58985755919.0,314712.0,14754.270859,null,1.979900998,14754.235833]},"self_profile":null,"check":false,"release":true,"state":{"IncrementalPatched":{"index":0,"name":"println","path":"0-println.patch"}}},{"stats":{"stats":[null,39942311180.0,76576.0,null,43154164019.0,311272.0,10546.972836,null,1.700117206,10546.954599]},"self_profile":null,"check":false,"release":true,"state":{"IncrementalPatched":{"index":1,"name":"minor change","path":"1-minor-change.patch"}}}],"name":"tokio-webpush-simple"}}}}